{
    "awake": "awoken",
    "be": "been",
    "bear": "borne",
    "beat": "beaten",
    "become": "become",
    "begin": "begun",
    "bend": "bent",
    "bet": "bet",
    "bid": "bidden",
    "bite": "bitten",
    "blow": "blown",
    "break": "broke",
    "bring": "brought",
    "broadcast": "broadcast",
    "build": "built",
    "burn": "burnt",
    "buy": "bought",
    "catch": "caught",
    "choose": "chosen",
    "come": "come",
    "cost": "cost",
    "cut": "cut",
    "deal": "dealt",
    "do": "done",
    "draw": "drawn",
    "drink": "drunk",
    "drive": "driven",
    "eat": "eaten",
    "fall": "fallen",
    "feel": "felt",
    "fight": "fought",
    "find": "found",
    "fly": "flown",
    "foretell": "foretold",
    "forget": "forgotten",
    "forgive": "forgiven",
    "freeze": "frore",
    "get": "got",
    "give": "given",
    "gnaw": "gnawn",
    "go": "gone",
    "grow": "grown",
    "have": "had",
    "hear": "heard",
    "help": "holpen",
    "hide": "hid",
    "hold": "holden",
    "hit": "hit",
    "hurt": "hurt",
    "keep": "kept",
    "knit": "knitten",
    "know": "known",
    "lay": "laid",
    "leave": "left",
    "lend": "lent",
    "let": "let",
    "light": "lit",
    "load": "loaden",
    "lose": "lorn",
    "make": "made",
    "mean": "meant",
    "meet": "met",
    "overrun": "overrun",
    "pay": "paid",
    "put": "put",
    "quit": "quit",
    "reach": "raught",
    "read": "read",
    "ride": "ridden",
    "ring": "rung",
    "rise": "ris",
    "run": "run",
    "say": "said",
    "see": "seen",
    "sell": "sold",
    "send": "sent",
    "set": "set",
    "shoot": "shot",
    "shut": "shut",
    "sing": "sung",
    "sit": "sat",
    "ski": "ski",
    "sleep": "slept",
    "slide": "slid",
    "speak": "spoke",
    "spend": "spent",
    "spoil": "spoilt",
    "spin": "spun",
    "stand": "stood",
    "stay": "staid",
    "swear": "sworn",
    "swim": "swum",
    "swing": "swung",
    "take": "took",
    "teach": "taught",
    "tear": "torn",
    "tell": "told",
    "think": "thought",
    "throw": "thrown",
    "understand": "understood",
    "upset": "upset",
    "uphold": "upheld",
    "wake": "woken",
    "wash": "washen",
    "wear": "worn",
    "weave": "wove",
    "win": "won",
    "work": "wrought",
    "wrap": "wrapt",
    "write": "written"
}